dotextensions/__init__.py
dotextensions/server/__init__.py
dotextensions/server/__main__.py
dotextensions/server/agent.py
dotextensions/server/handlers/__init__.py
dotextensions/server/handlers/basic_handlers.py
dotextensions/server/handlers/gohandler.py
dotextensions/server/handlers/har2httphandler.py
dotextensions/server/handlers/http2har.py
dotextensions/server/handlers/http2postman.py
dotextensions/server/handlers/postman2http.py
dotextensions/server/models/__init__.py
dotextensions/server/models/har.py
dotextensions/server/postman/__init__.py
dotextensions/server/postman2_1/__init__.py
dotextensions/server/server.py
dotextensions/server/utils.py
dotextensions/version/__init__.py
dotextensions/version/__main__.py
dothttp/__init__.py
dothttp/__main__.py
dothttp/__version__.py
dothttp/auth/__init__.py
dothttp/auth/azure_auth.py
dothttp/exceptions.py
dothttp/http.tx
dothttp/models/__init__.py
dothttp/models/computed.py
dothttp/models/parse_models.py
dothttp/parse/__init__.py
dothttp/parse/dsl_jsonparser.py
dothttp/parse/request_base.py
dothttp/postScript.js
dothttp/property_schema.py
dothttp/script/__init__.py
dothttp/script/js3py.py
dothttp/utils/__init__.py
dothttp/utils/common.py
dothttp/utils/constants.py
dothttp/utils/curl_utils.py
dothttp/utils/json_utils.py
dothttp/utils/log_utils.py
dothttp/utils/property_util.py
dothttp_test/__init__.py
dothttp_test/__main__.py
dothttp_test/conftest.py
dothttp_test/dothttp_test.py
dothttp_req-0.0.43.dist-info/LICENSE.txt
dothttp_req-0.0.43.dist-info/METADATA
dothttp_req-0.0.43.dist-info/WHEEL
dothttp_req-0.0.43.dist-info/entry_points.txt
dothttp_req-0.0.43.dist-info/RECORD
