Metadata-Version: 2.1
Name: dothttp-req
Version: 0.0.43
Summary: Dothttp is Simple http client for testing and development
License: MIT
Author: Prasanth
Author-email: kesavarapu.siva@gmail.com
Requires-Python: >=3.8,<3.14
Classifier: License :: OSI Approved :: MIT License
Classifier: Operating System :: OS Independent
Classifier: Programming Language :: Python :: 3
Classifier: Programming Language :: Python :: 3.8
Classifier: Programming Language :: Python :: 3.9
Classifier: Programming Language :: Python :: 3.10
Classifier: Programming Language :: Python :: 3.11
Classifier: Programming Language :: Python :: 3.12
Classifier: Programming Language :: Python :: 3.13
Provides-Extra: js
Requires-Dist: faker (==33.1.0)
Requires-Dist: jsonschema (==4.23.0)
Requires-Dist: jstyleson (==0.0.2)
Requires-Dist: msal (==1.31.1)
Requires-Dist: parsys-requests-unixsocket (==0.3.2)
Requires-Dist: pyyaml (==6.0.2)
Requires-Dist: requests (==2.32.3)
Requires-Dist: requests-aws4auth (==1.3.1)
Requires-Dist: requests-hawk (==1.2.1)
Requires-Dist: requests-ntlm (==1.3.0)
Requires-Dist: requests-pkcs12 (==1.25)
Requires-Dist: restrictedpython (==7.4)
Requires-Dist: textx (==4.1.0)
Requires-Dist: toml (==0.10.2)
Requires-Dist: xmltodict (>=0.14.2,<0.15.0)
Project-URL: Bug Tracker, https://github.com/cedric05/dothttp
